{
  "isotope": {
    "z": 5,
    "n": 5,
    "a": 10,
    "symbol": "B",
    "name": "10B",
    "parity": "oo"
  },
  "engine": {
    "name": "hecke-engine",
    "version": "0.8.0",
    "commit": "62d305e",
    "binary": "hecke-bigint (v9)"
  },
  "tr_alt": {
    "terms": [
      [
        -22,
        "-1"
      ],
      [
        -21,
        "-1"
      ],
      [
        -19,
        "3"
      ],
      [
        -17,
        "-5"
      ],
      [
        -16,
        "-7"
      ],
      [
        -15,
        "4"
      ],
      [
        -14,
        "8"
      ],
      [
        -13,
        "3"
      ],
      [
        -12,
        "-13"
      ],
      [
        -11,
        "-9"
      ],
      [
        -10,
        "3"
      ],
      [
        -9,
        "14"
      ],
      [
        -8,
        "9"
      ],
      [
        -7,
        "-9"
      ],
      [
        -6,
        "-23"
      ],
      [
        -5,
        "-5"
      ],
      [
        -4,
        "34"
      ],
      [
        -3,
        "31"
      ],
      [
        -2,
        "-34"
      ],
      [
        -1,
        "-53"
      ],
      [
        0,
        "36"
      ],
      [
        1,
        "58"
      ],
      [
        2,
        "-75"
      ],
      [
        3,
        "-64"
      ],
      [
        4,
        "235"
      ],
      [
        5,
        "220"
      ],
      [
        6,
        "-513"
      ],
      [
        7,
        "-964"
      ],
      [
        8,
        "353"
      ],
      [
        9,
        "2847"
      ],
      [
        10,
        "2228"
      ],
      [
        11,
        "-5364"
      ],
      [
        12,
        "-11395"
      ],
      [
        13,
        "3904"
      ],
      [
        14,
        "31319"
      ],
      [
        15,
        "12708"
      ],
      [
        16,
        "-57025"
      ],
      [
        17,
        "-50739"
      ],
      [
        18,
        "63346"
      ],
      [
        19,
        "53580"
      ],
      [
        20,
        "-39501"
      ],
      [
        21,
        "239621"
      ],
      [
        22,
        "215891"
      ],
      [
        23,
        "-1474916"
      ],
      [
        24,
        "-1757004"
      ],
      [
        25,
        "4593611"
      ],
      [
        26,
        "8203529"
      ],
      [
        27,
        "-9684025"
      ],
      [
        28,
        "-27585674"
      ],
      [
        29,
        "12506197"
      ],
      [
        30,
        "74263143"
      ],
      [
        31,
        "2640029"
      ],
      [
        32,
        "-168503518"
      ],
      [
        33,
        "-74428680"
      ],
      [
        34,
        "331400586"
      ],
      [
        35,
        "280384649"
      ],
      [
        36,
        "-573472996"
      ],
      [
        37,
        "-757413281"
      ],
      [
        38,
        "876188396"
      ],
      [
        39,
        "1728872563"
      ],
      [
        40,
        "-1164283821"
      ],
      [
        41,
        "-3540028928"
      ],
      [
        42,
        "1262063259"
      ],
      [
        43,
        "6696165452"
      ],
      [
        44,
        "-823615017"
      ],
      [
        45,
        "-11879220903"
      ],
      [
        46,
        "-763756199"
      ],
      [
        47,
        "19897383920"
      ],
      [
        48,
        "4472723079"
      ],
      [
        49,
        "-31518853147"
      ],
      [
        50,
        "-11651633209"
      ],
      [
        51,
        "47178484667"
      ],
      [
        52,
        "23864828249"
      ],
      [
        53,
        "-66623806687"
      ],
      [
        54,
        "-42498364834"
      ],
      [
        55,
        "88645508000"
      ],
      [
        56,
        "68186053754"
      ],
      [
        57,
        "-111054300140"
      ],
      [
        58,
        "-100252541477"
      ],
      [
        59,
        "130982842998"
      ],
      [
        60,
        "136443450707"
      ],
      [
        61,
        "-145439757421"
      ],
      [
        62,
        "-173138109753"
      ],
      [
        63,
        "151918528903"
      ],
      [
        64,
        "206030516577"
      ],
      [
        65,
        "-148858837417"
      ],
      [
        66,
        "-231037654922"
      ],
      [
        67,
        "135875937091"
      ],
      [
        68,
        "245099857260"
      ],
      [
        69,
        "-113814832955"
      ],
      [
        70,
        "-246637440717"
      ],
      [
        71,
        "84725257489"
      ],
      [
        72,
        "235639418230"
      ],
      [
        73,
        "-51758791037"
      ],
      [
        74,
        "-213520996091"
      ],
      [
        75,
        "18865049887"
      ],
      [
        76,
        "182889569360"
      ],
      [
        77,
        "9836411923"
      ],
      [
        78,
        "-147241749928"
      ],
      [
        79,
        "-30953098174"
      ],
      [
        80,
        "110518586743"
      ],
      [
        81,
        "42688315037"
      ],
      [
        82,
        "-76484037564"
      ],
      [
        83,
        "-45282762138"
      ],
      [
        84,
        "48040182486"
      ],
      [
        85,
        "40784407257"
      ],
      [
        86,
        "-26716997007"
      ],
      [
        87,
        "-32233188876"
      ],
      [
        88,
        "12551950933"
      ],
      [
        89,
        "22636855423"
      ],
      [
        90,
        "-4403002363"
      ],
      [
        91,
        "-14177108864"
      ],
      [
        92,
        "534356997"
      ],
      [
        93,
        "7904358884"
      ],
      [
        94,
        "787470905"
      ],
      [
        95,
        "-3899660595"
      ],
      [
        96,
        "-899826030"
      ],
      [
        97,
        "1683956415"
      ],
      [
        98,
        "621066430"
      ],
      [
        99,
        "-625000118"
      ],
      [
        100,
        "-333085085"
      ],
      [
        101,
        "193062356"
      ],
      [
        102,
        "147303672"
      ],
      [
        103,
        "-46380872"
      ],
      [
        104,
        "-54665387"
      ],
      [
        105,
        "7009096"
      ],
      [
        106,
        "17052889"
      ],
      [
        107,
        "238163"
      ],
      [
        108,
        "-4442693"
      ],
      [
        109,
        "-560978"
      ],
      [
        110,
        "954893"
      ],
      [
        111,
        "203221"
      ],
      [
        112,
        "-166320"
      ],
      [
        113,
        "-44810"
      ],
      [
        114,
        "22851"
      ],
      [
        115,
        "6505"
      ],
      [
        116,
        "-2362"
      ],
      [
        117,
        "-578"
      ],
      [
        118,
        "166"
      ],
      [
        119,
        "24"
      ],
      [
        120,
        "-6"
      ]
    ]
  },
  "net": {
    "terms": [
      [
        -7,
        "1"
      ],
      [
        -5,
        "-5"
      ],
      [
        -4,
        "-5"
      ],
      [
        -3,
        "9"
      ],
      [
        -2,
        "13"
      ],
      [
        0,
        "-9"
      ],
      [
        1,
        "-18"
      ],
      [
        2,
        "-25"
      ],
      [
        3,
        "9"
      ],
      [
        4,
        "75"
      ],
      [
        5,
        "22"
      ],
      [
        6,
        "-160"
      ],
      [
        7,
        "-76"
      ],
      [
        8,
        "319"
      ],
      [
        9,
        "296"
      ],
      [
        10,
        "-537"
      ],
      [
        11,
        "-1058"
      ],
      [
        12,
        "339"
      ],
      [
        13,
        "2922"
      ],
      [
        14,
        "2290"
      ],
      [
        15,
        "-5399"
      ],
      [
        16,
        "-11482"
      ],
      [
        17,
        "3899"
      ],
      [
        18,
        "31400"
      ],
      [
        19,
        "12767"
      ],
      [
        20,
        "-57308"
      ],
      [
        21,
        "-51002"
      ],
      [
        22,
        "66145"
      ],
      [
        23,
        "55523"
      ],
      [
        24,
        "-62152"
      ],
      [
        25,
        "222620"
      ],
      [
        26,
        "352958"
      ],
      [
        27,
        "-1346158"
      ],
      [
        28,
        "-2406056"
      ],
      [
        29,
        "3807372"
      ],
      [
        30,
        "10683179"
      ],
      [
        31,
        "-5791163"
      ],
      [
        32,
        "-35329172"
      ],
      [
        33,
        "-3461833"
      ],
      [
        34,
        "93927019"
      ],
      [
        35,
        "58062935"
      ],
      [
        36,
        "-207547924"
      ],
      [
        37,
        "-240078709"
      ],
      [
        38,
        "383107809"
      ],
      [
        39,
        "712624885"
      ],
      [
        40,
        "-573391336"
      ],
      [
        41,
        "-1752417056"
      ],
      [
        42,
        "611592278"
      ],
      [
        43,
        "3764930250"
      ],
      [
        44,
        "-130488510"
      ],
      [
        45,
        "-7262243754"
      ],
      [
        46,
        "-1505876634"
      ],
      [
        47,
        "12790338069"
      ],
      [
        48,
        "5216659810"
      ],
      [
        49,
        "-20809689325"
      ],
      [
        50,
        "-12124707662"
      ],
      [
        51,
        "31554089149"
      ],
      [
        52,
        "23364370715"
      ],
      [
        53,
        "-44906529460"
      ],
      [
        54,
        "-39795344319"
      ],
      [
        55,
        "60328735270"
      ],
      [
        56,
        "61681677620"
      ],
      [
        57,
        "-76862780505"
      ],
      [
        58,
        "-88423194825"
      ],
      [
        59,
        "93199868992"
      ],
      [
        60,
        "118431330151"
      ],
      [
        61,
        "-107797016518"
      ],
      [
        62,
        "-149218706253"
      ],
      [
        63,
        "119024424352"
      ],
      [
        64,
        "177723382439"
      ],
      [
        65,
        "-125339526951"
      ],
      [
        66,
        "-200821923219"
      ],
      [
        67,
        "125493417359"
      ],
      [
        68,
        "215916529141"
      ],
      [
        69,
        "-118767628895"
      ],
      [
        70,
        "-221437106058"
      ],
      [
        71,
        "105210669307"
      ],
      [
        72,
        "217107990170"
      ],
      [
        73,
        "-85805982549"
      ],
      [
        74,
        "-203902282455"
      ],
      [
        75,
        "62480184615"
      ],
      [
        76,
        "183720614920"
      ],
      [
        77,
        "-37878183981"
      ],
      [
        78,
        "-158930758905"
      ],
      [
        79,
        "14900901049"
      ],
      [
        80,
        "131934977210"
      ],
      [
        81,
        "3897203950"
      ],
      [
        82,
        "-104878175569"
      ],
      [
        83,
        "-16868101894"
      ],
      [
        84,
        "79510986423"
      ],
      [
        85,
        "23590085227"
      ],
      [
        86,
        "-57145157132"
      ],
      [
        87,
        "-24829598214"
      ],
      [
        88,
        "38629296017"
      ],
      [
        89,
        "22170249329"
      ],
      [
        90,
        "-24321778024"
      ],
      [
        91,
        "-17467766171"
      ],
      [
        92,
        "14092649650"
      ],
      [
        93,
        "12342866936"
      ],
      [
        94,
        "-7399174221"
      ],
      [
        95,
        "-7874838183"
      ],
      [
        96,
        "3443324373"
      ],
      [
        97,
        "4545090047"
      ],
      [
        98,
        "-1368401094"
      ],
      [
        99,
        "-2370500853"
      ],
      [
        100,
        "427847256"
      ],
      [
        101,
        "1113508156"
      ],
      [
        102,
        "-77342398"
      ],
      [
        103,
        "-468660500"
      ],
      [
        104,
        "-16739572"
      ],
      [
        105,
        "175553093"
      ],
      [
        106,
        "24121729"
      ],
      [
        107,
        "-58069749"
      ],
      [
        108,
        "-13751908"
      ],
      [
        109,
        "16830154"
      ],
      [
        110,
        "5604020"
      ],
      [
        111,
        "-4248624"
      ],
      [
        112,
        "-1782594"
      ],
      [
        113,
        "932218"
      ],
      [
        114,
        "447404"
      ],
      [
        115,
        "-177754"
      ],
      [
        116,
        "-86356"
      ],
      [
        117,
        "29105"
      ],
      [
        118,
        "12021"
      ],
      [
        119,
        "-3880"
      ],
      [
        120,
        "-1049"
      ],
      [
        121,
        "368"
      ],
      [
        122,
        "37"
      ],
      [
        123,
        "-18"
      ],
      [
        124,
        "1"
      ]
    ]
  },
  "observable": {
    "terms": [
      [
        17,
        "-1"
      ],
      [
        18,
        "9"
      ],
      [
        19,
        "19"
      ],
      [
        20,
        "-233"
      ],
      [
        21,
        "-210"
      ],
      [
        22,
        "2999"
      ],
      [
        23,
        "2053"
      ],
      [
        24,
        "-25526"
      ],
      [
        25,
        "-18699"
      ],
      [
        26,
        "160959"
      ],
      [
        27,
        "144729"
      ],
      [
        28,
        "-797411"
      ],
      [
        29,
        "-910771"
      ],
      [
        30,
        "3208262"
      ],
      [
        31,
        "4679656"
      ],
      [
        32,
        "-10667640"
      ],
      [
        33,
        "-20019471"
      ],
      [
        34,
        "29430134"
      ],
      [
        35,
        "72789658"
      ],
      [
        36,
        "-66359722"
      ],
      [
        37,
        "-228989439"
      ],
      [
        38,
        "115120011"
      ],
      [
        39,
        "632478814"
      ],
      [
        40,
        "-117275917"
      ],
      [
        41,
        "-1552013543"
      ],
      [
        42,
        "-116082899"
      ],
      [
        43,
        "3415897076"
      ],
      [
        44,
        "1024260746"
      ],
      [
        45,
        "-6795560174"
      ],
      [
        46,
        "-3430238027"
      ],
      [
        47,
        "12296641921"
      ],
      [
        48,
        "8618626391"
      ],
      [
        49,
        "-20343742733"
      ],
      [
        50,
        "-18263421759"
      ],
      [
        51,
        "30904424628"
      ],
      [
        52,
        "34131187247"
      ],
      [
        53,
        "-43263238606"
      ],
      [
        54,
        "-57568832471"
      ],
      [
        55,
        "55979816066"
      ],
      [
        56,
        "88907479328"
      ],
      [
        57,
        "-67107640052"
      ],
      [
        58,
        "-127008442048"
      ],
      [
        59,
        "74621826677"
      ],
      [
        60,
        "169170245494"
      ],
      [
        61,
        "-76877283074"
      ],
      [
        62,
        "-211482549760"
      ],
      [
        63,
        "72889683556"
      ],
      [
        64,
        "249514756244"
      ],
      [
        65,
        "-62346323194"
      ],
      [
        66,
        "-279084497164"
      ],
      [
        67,
        "45449799240"
      ],
      [
        68,
        "296860917844"
      ],
      [
        69,
        "-22827467602"
      ],
      [
        70,
        "-300710432542"
      ],
      [
        71,
        "-4321561200"
      ],
      [
        72,
        "289866857082"
      ],
      [
        73,
        "33909551618"
      ],
      [
        74,
        "-265060157430"
      ],
      [
        75,
        "-62786446016"
      ],
      [
        76,
        "228625808640"
      ],
      [
        77,
        "87058298056"
      ],
      [
        78,
        "-184445235370"
      ],
      [
        79,
        "-102992092914"
      ],
      [
        80,
        "137509814362"
      ],
      [
        81,
        "108200428609"
      ],
      [
        82,
        "-93047588261"
      ],
      [
        83,
        "-102535301649"
      ],
      [
        84,
        "55423096645"
      ],
      [
        85,
        "88201690142"
      ],
      [
        86,
        "-27219192659"
      ],
      [
        87,
        "-68997318851"
      ],
      [
        88,
        "8876917518"
      ],
      [
        89,
        "49040420941"
      ],
      [
        90,
        "987589711"
      ],
      [
        91,
        "-31574272557"
      ],
      [
        92,
        "-4786910747"
      ],
      [
        93,
        "18319790829"
      ],
      [
        94,
        "5067197538"
      ],
      [
        95,
        "-9503433236"
      ],
      [
        96,
        "-3857240884"
      ],
      [
        97,
        "4355092849"
      ],
      [
        98,
        "2411561318"
      ],
      [
        99,
        "-1729465722"
      ],
      [
        100,
        "-1289091002"
      ],
      [
        101,
        "574877977"
      ],
      [
        102,
        "597527707"
      ],
      [
        103,
        "-148014694"
      ],
      [
        104,
        "-240978245"
      ],
      [
        105,
        "22309429"
      ],
      [
        106,
        "84374121"
      ],
      [
        107,
        "2889132"
      ],
      [
        108,
        "-25513858"
      ],
      [
        109,
        "-3563282"
      ],
      [
        110,
        "6617165"
      ],
      [
        111,
        "1485369"
      ],
      [
        112,
        "-1460121"
      ],
      [
        113,
        "-413211"
      ],
      [
        114,
        "271115"
      ],
      [
        115,
        "82274"
      ],
      [
        116,
        "-41467"
      ],
      [
        117,
        "-11334"
      ],
      [
        118,
        "4971"
      ],
      [
        119,
        "948"
      ],
      [
        120,
        "-416"
      ],
      [
        121,
        "-30"
      ],
      [
        122,
        "18"
      ],
      [
        123,
        "-1"
      ]
    ]
  },
  "coral": {
    "terms": [
      [
        -7,
        "1"
      ],
      [
        -5,
        "-5"
      ],
      [
        -4,
        "-5"
      ],
      [
        -3,
        "9"
      ],
      [
        -2,
        "13"
      ],
      [
        0,
        "-9"
      ],
      [
        1,
        "-18"
      ],
      [
        2,
        "-25"
      ],
      [
        3,
        "9"
      ],
      [
        4,
        "75"
      ],
      [
        5,
        "22"
      ],
      [
        6,
        "-160"
      ],
      [
        7,
        "-76"
      ],
      [
        8,
        "319"
      ],
      [
        9,
        "296"
      ],
      [
        10,
        "-537"
      ],
      [
        11,
        "-1058"
      ],
      [
        12,
        "339"
      ],
      [
        13,
        "2922"
      ],
      [
        14,
        "2290"
      ],
      [
        15,
        "-5399"
      ],
      [
        16,
        "-11482"
      ],
      [
        17,
        "3900"
      ],
      [
        18,
        "31391"
      ],
      [
        19,
        "12748"
      ],
      [
        20,
        "-57075"
      ],
      [
        21,
        "-50792"
      ],
      [
        22,
        "63146"
      ],
      [
        23,
        "53470"
      ],
      [
        24,
        "-36626"
      ],
      [
        25,
        "241319"
      ],
      [
        26,
        "191999"
      ],
      [
        27,
        "-1490887"
      ],
      [
        28,
        "-1608645"
      ],
      [
        29,
        "4718143"
      ],
      [
        30,
        "7474917"
      ],
      [
        31,
        "-10470819"
      ],
      [
        32,
        "-24661532"
      ],
      [
        33,
        "16557638"
      ],
      [
        34,
        "64496885"
      ],
      [
        35,
        "-14726723"
      ],
      [
        36,
        "-141188202"
      ],
      [
        37,
        "-11089270"
      ],
      [
        38,
        "267987798"
      ],
      [
        39,
        "80146071"
      ],
      [
        40,
        "-456115419"
      ],
      [
        41,
        "-200403513"
      ],
      [
        42,
        "727675177"
      ],
      [
        43,
        "349033174"
      ],
      [
        44,
        "-1154749256"
      ],
      [
        45,
        "-466683580"
      ],
      [
        46,
        "1924361393"
      ],
      [
        47,
        "493696148"
      ],
      [
        48,
        "-3401966581"
      ],
      [
        49,
        "-465946592"
      ],
      [
        50,
        "6138714097"
      ],
      [
        51,
        "649664521"
      ],
      [
        52,
        "-10766816532"
      ],
      [
        53,
        "-1643290854"
      ],
      [
        54,
        "17773488152"
      ],
      [
        55,
        "4348919204"
      ],
      [
        56,
        "-27225801708"
      ],
      [
        57,
        "-9755140453"
      ],
      [
        58,
        "38585247223"
      ],
      [
        59,
        "18578042315"
      ],
      [
        60,
        "-50738915343"
      ],
      [
        61,
        "-30919733444"
      ],
      [
        62,
        "62263843507"
      ],
      [
        63,
        "46134740796"
      ],
      [
        64,
        "-71791373805"
      ],
      [
        65,
        "-62993203757"
      ],
      [
        66,
        "78262573945"
      ],
      [
        67,
        "80043618119"
      ],
      [
        68,
        "-80944388703"
      ],
      [
        69,
        "-95940161293"
      ],
      [
        70,
        "79273326484"
      ],
      [
        71,
        "109532230507"
      ],
      [
        72,
        "-72758866912"
      ],
      [
        73,
        "-119715534167"
      ],
      [
        74,
        "61157874975"
      ],
      [
        75,
        "125266630631"
      ],
      [
        76,
        "-44905193720"
      ],
      [
        77,
        "-124936482037"
      ],
      [
        78,
        "25514476465"
      ],
      [
        79,
        "117892993963"
      ],
      [
        80,
        "-5574837152"
      ],
      [
        81,
        "-104303224659"
      ],
      [
        82,
        "-11830587308"
      ],
      [
        83,
        "85667199755"
      ],
      [
        84,
        "24087889778"
      ],
      [
        85,
        "-64611604915"
      ],
      [
        86,
        "-29925964473"
      ],
      [
        87,
        "44167720637"
      ],
      [
        88,
        "29752378499"
      ],
      [
        89,
        "-26870171612"
      ],
      [
        90,
        "-25309367735"
      ],
      [
        91,
        "14106506386"
      ],
      [
        92,
        "18879560397"
      ],
      [
        93,
        "-5976923893"
      ],
      [
        94,
        "-12466371759"
      ],
      [
        95,
        "1628595053"
      ],
      [
        96,
        "7300565257"
      ],
      [
        97,
        "189997198"
      ],
      [
        98,
        "-3779962412"
      ],
      [
        99,
        "-641035131"
      ],
      [
        100,
        "1716938258"
      ],
      [
        101,
        "538630179"
      ],
      [
        102,
        "-674870105"
      ],
      [
        103,
        "-320645806"
      ],
      [
        104,
        "224238673"
      ],
      [
        105,
        "153243664"
      ],
      [
        106,
        "-60252392"
      ],
      [
        107,
        "-60958881"
      ],
      [
        108,
        "11761950"
      ],
      [
        109,
        "20393436"
      ],
      [
        110,
        "-1013145"
      ],
      [
        111,
        "-5733993"
      ],
      [
        112,
        "-322473"
      ],
      [
        113,
        "1345429"
      ],
      [
        114,
        "176289"
      ],
      [
        115,
        "-260028"
      ],
      [
        116,
        "-44889"
      ],
      [
        117,
        "40439"
      ],
      [
        118,
        "7050"
      ],
      [
        119,
        "-4828"
      ],
      [
        120,
        "-633"
      ],
      [
        121,
        "398"
      ],
      [
        122,
        "19"
      ],
      [
        123,
        "-17"
      ],
      [
        124,
        "1"
      ]
    ]
  },
  "jets": [
    {
      "terms": [
        [
          19,
          "1"
        ],
        [
          20,
          "-6"
        ],
        [
          21,
          "-24"
        ],
        [
          22,
          "150"
        ],
        [
          23,
          "314"
        ],
        [
          24,
          "-1830"
        ],
        [
          25,
          "-3013"
        ],
        [
          26,
          "14491"
        ],
        [
          27,
          "23218"
        ],
        [
          28,
          "-83338"
        ],
        [
          29,
          "-147226"
        ],
        [
          30,
          "367476"
        ],
        [
          31,
          "775476"
        ],
        [
          32,
          "-1268855"
        ],
        [
          33,
          "-3428219"
        ],
        [
          34,
          "3383661"
        ],
        [
          35,
          "12878477"
        ],
        [
          36,
          "-6330584"
        ],
        [
          37,
          "-41629340"
        ],
        [
          38,
          "4093013"
        ],
        [
          39,
          "117098386"
        ],
        [
          40,
          "27144290"
        ],
        [
          41,
          "-289272540"
        ],
        [
          42,
          "-152761754"
        ],
        [
          43,
          "631824268"
        ],
        [
          44,
          "514724366"
        ],
        [
          45,
          "-1224915138"
        ],
        [
          46,
          "-1366610829"
        ],
        [
          47,
          "2108282748"
        ],
        [
          48,
          "3082766924"
        ],
        [
          49,
          "-3204306082"
        ],
        [
          50,
          "-6106649072"
        ],
        [
          51,
          "4233168417"
        ],
        [
          52,
          "10812714958"
        ],
        [
          53,
          "-4666841560"
        ],
        [
          54,
          "-17290917472"
        ],
        [
          55,
          "3777991392"
        ],
        [
          56,
          "25114784743"
        ],
        [
          57,
          "-818165759"
        ],
        [
          58,
          "-33198257694"
        ],
        [
          59,
          "-4694574260"
        ],
        [
          60,
          "39852118204"
        ],
        [
          61,
          "12665393388"
        ],
        [
          62,
          "-43099843452"
        ],
        [
          63,
          "-22222263496"
        ],
        [
          64,
          "41213915998"
        ],
        [
          65,
          "31750851086"
        ],
        [
          66,
          "-33323507882"
        ],
        [
          67,
          "-39219727970"
        ],
        [
          68,
          "19873444320"
        ],
        [
          69,
          "42735966952"
        ],
        [
          70,
          "-2725152690"
        ],
        [
          71,
          "-41156826940"
        ],
        [
          72,
          "-15203305920"
        ],
        [
          73,
          "34525005416"
        ],
        [
          74,
          "30687760440"
        ],
        [
          75,
          "-24133760432"
        ],
        [
          76,
          "-41097424356"
        ],
        [
          77,
          "12164114412"
        ],
        [
          78,
          "45116595498"
        ],
        [
          79,
          "-1016570744"
        ],
        [
          80,
          "-43017943756"
        ],
        [
          81,
          "-7403298576"
        ],
        [
          82,
          "36401052460"
        ],
        [
          83,
          "12167916879"
        ],
        [
          84,
          "-27536028906"
        ],
        [
          85,
          "-13416709512"
        ],
        [
          86,
          "18604640234"
        ],
        [
          87,
          "12073969530"
        ],
        [
          88,
          "-11135351988"
        ],
        [
          89,
          "-9373243851"
        ],
        [
          90,
          "5795332235"
        ],
        [
          91,
          "6412750610"
        ],
        [
          92,
          "-2518873586"
        ],
        [
          93,
          "-3898663698"
        ],
        [
          94,
          "819862864"
        ],
        [
          95,
          "2109592148"
        ],
        [
          96,
          "-109670431"
        ],
        [
          97,
          "-1013124763"
        ],
        [
          98,
          "-95532539"
        ],
        [
          99,
          "428985277"
        ],
        [
          100,
          "102378072"
        ],
        [
          101,
          "-158461612"
        ],
        [
          102,
          "-62174123"
        ],
        [
          103,
          "50265610"
        ],
        [
          104,
          "28751942"
        ],
        [
          105,
          "-13378172"
        ],
        [
          106,
          "-10805158"
        ],
        [
          107,
          "2882964"
        ],
        [
          108,
          "3357334"
        ],
        [
          109,
          "-474090"
        ],
        [
          110,
          "-860389"
        ],
        [
          111,
          "53052"
        ],
        [
          112,
          "178872"
        ],
        [
          113,
          "-3014"
        ],
        [
          114,
          "-29188"
        ],
        [
          115,
          "39"
        ],
        [
          116,
          "3522"
        ],
        [
          117,
          "-40"
        ],
        [
          118,
          "-280"
        ],
        [
          119,
          "12"
        ],
        [
          120,
          "11"
        ],
        [
          121,
          "-1"
        ]
      ]
    },
    {
      "terms": [
        [
          17,
          "-1"
        ],
        [
          18,
          "9"
        ],
        [
          19,
          "18"
        ],
        [
          20,
          "-227"
        ],
        [
          21,
          "-186"
        ],
        [
          22,
          "2849"
        ],
        [
          23,
          "1739"
        ],
        [
          24,
          "-23696"
        ],
        [
          25,
          "-15686"
        ],
        [
          26,
          "146468"
        ],
        [
          27,
          "121511"
        ],
        [
          28,
          "-714073"
        ],
        [
          29,
          "-763545"
        ],
        [
          30,
          "2840786"
        ],
        [
          31,
          "3904180"
        ],
        [
          32,
          "-9398785"
        ],
        [
          33,
          "-16591252"
        ],
        [
          34,
          "26046473"
        ],
        [
          35,
          "59911181"
        ],
        [
          36,
          "-60029138"
        ],
        [
          37,
          "-187360099"
        ],
        [
          38,
          "111026998"
        ],
        [
          39,
          "515380428"
        ],
        [
          40,
          "-144420207"
        ],
        [
          41,
          "-1262741003"
        ],
        [
          42,
          "36678855"
        ],
        [
          43,
          "2784072808"
        ],
        [
          44,
          "509536380"
        ],
        [
          45,
          "-5570645036"
        ],
        [
          46,
          "-2063627198"
        ],
        [
          47,
          "10188359173"
        ],
        [
          48,
          "5535859467"
        ],
        [
          49,
          "-17139436651"
        ],
        [
          50,
          "-12156772687"
        ],
        [
          51,
          "26671256211"
        ],
        [
          52,
          "23318472289"
        ],
        [
          53,
          "-38596397046"
        ],
        [
          54,
          "-40277914999"
        ],
        [
          55,
          "52201824674"
        ],
        [
          56,
          "63792694585"
        ],
        [
          57,
          "-66289474293"
        ],
        [
          58,
          "-93810184354"
        ],
        [
          59,
          "79316400937"
        ],
        [
          60,
          "129318127290"
        ],
        [
          61,
          "-89542676462"
        ],
        [
          62,
          "-168382706308"
        ],
        [
          63,
          "95111947052"
        ],
        [
          64,
          "208300840246"
        ],
        [
          65,
          "-94097174280"
        ],
        [
          66,
          "-245760989282"
        ],
        [
          67,
          "84669527210"
        ],
        [
          68,
          "276987473524"
        ],
        [
          69,
          "-65563434554"
        ],
        [
          70,
          "-297985279852"
        ],
        [
          71,
          "36835265740"
        ],
        [
          72,
          "305070163002"
        ],
        [
          73,
          "-615453798"
        ],
        [
          74,
          "-295747917870"
        ],
        [
          75,
          "-38652685584"
        ],
        [
          76,
          "269723232996"
        ],
        [
          77,
          "74894183644"
        ],
        [
          78,
          "-229561830868"
        ],
        [
          79,
          "-101975522170"
        ],
        [
          80,
          "180527758118"
        ],
        [
          81,
          "115603727185"
        ],
        [
          82,
          "-129448640721"
        ],
        [
          83,
          "-114703218528"
        ],
        [
          84,
          "82959125551"
        ],
        [
          85,
          "101618399654"
        ],
        [
          86,
          "-45823832893"
        ],
        [
          87,
          "-81071288381"
        ],
        [
          88,
          "20012269506"
        ],
        [
          89,
          "58413664792"
        ],
        [
          90,
          "-4807742524"
        ],
        [
          91,
          "-37987023167"
        ],
        [
          92,
          "-2268037161"
        ],
        [
          93,
          "22218454527"
        ],
        [
          94,
          "4247334674"
        ],
        [
          95,
          "-11613025384"
        ],
        [
          96,
          "-3747570453"
        ],
        [
          97,
          "5368217612"
        ],
        [
          98,
          "2507093857"
        ],
        [
          99,
          "-2158450999"
        ],
        [
          100,
          "-1391469074"
        ],
        [
          101,
          "733339589"
        ],
        [
          102,
          "659701830"
        ],
        [
          103,
          "-198280304"
        ],
        [
          104,
          "-269730187"
        ],
        [
          105,
          "35687601"
        ],
        [
          106,
          "95179279"
        ],
        [
          107,
          "6168"
        ],
        [
          108,
          "-28871192"
        ],
        [
          109,
          "-3089192"
        ],
        [
          110,
          "7477554"
        ],
        [
          111,
          "1432317"
        ],
        [
          112,
          "-1638993"
        ],
        [
          113,
          "-410197"
        ],
        [
          114,
          "300303"
        ],
        [
          115,
          "82235"
        ],
        [
          116,
          "-44989"
        ],
        [
          117,
          "-11294"
        ],
        [
          118,
          "5251"
        ],
        [
          119,
          "936"
        ],
        [
          120,
          "-427"
        ],
        [
          121,
          "-29"
        ],
        [
          122,
          "18"
        ],
        [
          123,
          "-1"
        ]
      ]
    },
    {
      "terms": [
        [
          -2,
          "-1"
        ],
        [
          0,
          "2"
        ],
        [
          1,
          "-3"
        ],
        [
          2,
          "-9"
        ],
        [
          3,
          "14"
        ],
        [
          4,
          "38"
        ],
        [
          5,
          "-31"
        ],
        [
          6,
          "-128"
        ],
        [
          7,
          "22"
        ],
        [
          8,
          "350"
        ],
        [
          9,
          "183"
        ],
        [
          10,
          "-666"
        ],
        [
          11,
          "-1013"
        ],
        [
          12,
          "508"
        ],
        [
          13,
          "2990"
        ],
        [
          14,
          "2123"
        ],
        [
          15,
          "-5572"
        ],
        [
          16,
          "-11386"
        ],
        [
          17,
          "4125"
        ],
        [
          18,
          "31407"
        ],
        [
          19,
          "12541"
        ],
        [
          20,
          "-57181"
        ],
        [
          21,
          "-50651"
        ],
        [
          22,
          "63311"
        ],
        [
          23,
          "53423"
        ],
        [
          24,
          "-36804"
        ],
        [
          25,
          "241280"
        ],
        [
          26,
          "192140"
        ],
        [
          27,
          "-1490787"
        ],
        [
          28,
          "-1608733"
        ],
        [
          29,
          "4718024"
        ],
        [
          30,
          "7474944"
        ],
        [
          31,
          "-10470715"
        ],
        [
          32,
          "-24661514"
        ],
        [
          33,
          "16557567"
        ],
        [
          34,
          "64496852"
        ],
        [
          35,
          "-14726687"
        ],
        [
          36,
          "-141188173"
        ],
        [
          37,
          "-11089282"
        ],
        [
          38,
          "267987781"
        ],
        [
          39,
          "80146073"
        ],
        [
          40,
          "-456115413"
        ],
        [
          41,
          "-200403513"
        ],
        [
          42,
          "727675176"
        ],
        [
          43,
          "349033174"
        ],
        [
          44,
          "-1154749256"
        ],
        [
          45,
          "-466683580"
        ],
        [
          46,
          "1924361393"
        ],
        [
          47,
          "493696148"
        ],
        [
          48,
          "-3401966581"
        ],
        [
          49,
          "-465946592"
        ],
        [
          50,
          "6138714097"
        ],
        [
          51,
          "649664521"
        ],
        [
          52,
          "-10766816532"
        ],
        [
          53,
          "-1643290854"
        ],
        [
          54,
          "17773488152"
        ],
        [
          55,
          "4348919204"
        ],
        [
          56,
          "-27225801708"
        ],
        [
          57,
          "-9755140453"
        ],
        [
          58,
          "38585247223"
        ],
        [
          59,
          "18578042315"
        ],
        [
          60,
          "-50738915343"
        ],
        [
          61,
          "-30919733444"
        ],
        [
          62,
          "62263843507"
        ],
        [
          63,
          "46134740796"
        ],
        [
          64,
          "-71791373805"
        ],
        [
          65,
          "-62993203757"
        ],
        [
          66,
          "78262573945"
        ],
        [
          67,
          "80043618119"
        ],
        [
          68,
          "-80944388703"
        ],
        [
          69,
          "-95940161293"
        ],
        [
          70,
          "79273326484"
        ],
        [
          71,
          "109532230507"
        ],
        [
          72,
          "-72758866912"
        ],
        [
          73,
          "-119715534167"
        ],
        [
          74,
          "61157874975"
        ],
        [
          75,
          "125266630631"
        ],
        [
          76,
          "-44905193720"
        ],
        [
          77,
          "-124936482037"
        ],
        [
          78,
          "25514476465"
        ],
        [
          79,
          "117892993963"
        ],
        [
          80,
          "-5574837152"
        ],
        [
          81,
          "-104303224659"
        ],
        [
          82,
          "-11830587308"
        ],
        [
          83,
          "85667199755"
        ],
        [
          84,
          "24087889778"
        ],
        [
          85,
          "-64611604915"
        ],
        [
          86,
          "-29925964473"
        ],
        [
          87,
          "44167720637"
        ],
        [
          88,
          "29752378499"
        ],
        [
          89,
          "-26870171612"
        ],
        [
          90,
          "-25309367735"
        ],
        [
          91,
          "14106506386"
        ],
        [
          92,
          "18879560397"
        ],
        [
          93,
          "-5976923893"
        ],
        [
          94,
          "-12466371759"
        ],
        [
          95,
          "1628595053"
        ],
        [
          96,
          "7300565257"
        ],
        [
          97,
          "189997198"
        ],
        [
          98,
          "-3779962412"
        ],
        [
          99,
          "-641035131"
        ],
        [
          100,
          "1716938258"
        ],
        [
          101,
          "538630179"
        ],
        [
          102,
          "-674870105"
        ],
        [
          103,
          "-320645806"
        ],
        [
          104,
          "224238673"
        ],
        [
          105,
          "153243664"
        ],
        [
          106,
          "-60252392"
        ],
        [
          107,
          "-60958881"
        ],
        [
          108,
          "11761950"
        ],
        [
          109,
          "20393436"
        ],
        [
          110,
          "-1013145"
        ],
        [
          111,
          "-5733993"
        ],
        [
          112,
          "-322473"
        ],
        [
          113,
          "1345429"
        ],
        [
          114,
          "176289"
        ],
        [
          115,
          "-260028"
        ],
        [
          116,
          "-44889"
        ],
        [
          117,
          "40439"
        ],
        [
          118,
          "7050"
        ],
        [
          119,
          "-4828"
        ],
        [
          120,
          "-633"
        ],
        [
          121,
          "398"
        ],
        [
          122,
          "19"
        ],
        [
          123,
          "-17"
        ],
        [
          124,
          "1"
        ]
      ]
    },
    {
      "terms": [
        [
          -2,
          "-3"
        ],
        [
          0,
          "9"
        ],
        [
          1,
          "5"
        ],
        [
          2,
          "-17"
        ],
        [
          3,
          "-25"
        ],
        [
          4,
          "21"
        ],
        [
          5,
          "58"
        ],
        [
          6,
          "-2"
        ],
        [
          7,
          "-89"
        ],
        [
          8,
          "-51"
        ],
        [
          9,
          "96"
        ],
        [
          10,
          "124"
        ],
        [
          11,
          "-44"
        ],
        [
          12,
          "-180"
        ],
        [
          13,
          "-65"
        ],
        [
          14,
          "187"
        ],
        [
          15,
          "179"
        ],
        [
          16,
          "-116"
        ],
        [
          17,
          "-256"
        ],
        [
          18,
          "-10"
        ],
        [
          19,
          "255"
        ],
        [
          20,
          "125"
        ],
        [
          21,
          "-168"
        ],
        [
          22,
          "-203"
        ],
        [
          23,
          "49"
        ],
        [
          24,
          "213"
        ],
        [
          25,
          "58"
        ],
        [
          26,
          "-159"
        ],
        [
          27,
          "-126"
        ],
        [
          28,
          "88"
        ],
        [
          29,
          "139"
        ],
        [
          30,
          "-20"
        ],
        [
          31,
          "-113"
        ],
        [
          32,
          "-25"
        ],
        [
          33,
          "73"
        ],
        [
          34,
          "37"
        ],
        [
          35,
          "-36"
        ],
        [
          36,
          "-30"
        ],
        [
          37,
          "12"
        ],
        [
          38,
          "17"
        ],
        [
          39,
          "-2"
        ],
        [
          40,
          "-6"
        ],
        [
          42,
          "1"
        ]
      ]
    },
    {
      "terms": [
        [
          -4,
          "1"
        ],
        [
          -2,
          "2"
        ],
        [
          -1,
          "-2"
        ],
        [
          0,
          "-7"
        ],
        [
          1,
          "1"
        ],
        [
          2,
          "5"
        ],
        [
          3,
          "4"
        ],
        [
          4,
          "-6"
        ],
        [
          5,
          "-2"
        ],
        [
          6,
          "4"
        ],
        [
          7,
          "1"
        ],
        [
          8,
          "8"
        ],
        [
          9,
          "1"
        ],
        [
          10,
          "-14"
        ],
        [
          11,
          "2"
        ],
        [
          12,
          "25"
        ],
        [
          13,
          "7"
        ],
        [
          14,
          "-39"
        ],
        [
          15,
          "-24"
        ],
        [
          16,
          "32"
        ],
        [
          17,
          "36"
        ],
        [
          18,
          "-5"
        ],
        [
          19,
          "-47"
        ],
        [
          20,
          "-26"
        ],
        [
          21,
          "28"
        ],
        [
          22,
          "44"
        ],
        [
          23,
          "5"
        ],
        [
          24,
          "-42"
        ],
        [
          25,
          "-26"
        ],
        [
          26,
          "22"
        ],
        [
          27,
          "31"
        ],
        [
          28,
          "-1"
        ],
        [
          29,
          "-23"
        ],
        [
          30,
          "-7"
        ],
        [
          31,
          "10"
        ],
        [
          32,
          "7"
        ],
        [
          33,
          "-2"
        ],
        [
          34,
          "-4"
        ],
        [
          36,
          "1"
        ]
      ]
    },
    {
      "terms": [
        [
          -4,
          "-4"
        ],
        [
          -3,
          "3"
        ],
        [
          -2,
          "9"
        ],
        [
          -1,
          "1"
        ],
        [
          0,
          "-5"
        ],
        [
          1,
          "-15"
        ],
        [
          2,
          "-1"
        ],
        [
          3,
          "10"
        ],
        [
          4,
          "16"
        ],
        [
          5,
          "1"
        ],
        [
          6,
          "-23"
        ],
        [
          7,
          "-9"
        ],
        [
          8,
          "10"
        ],
        [
          9,
          "12"
        ],
        [
          10,
          "17"
        ],
        [
          11,
          "1"
        ],
        [
          12,
          "-18"
        ],
        [
          13,
          "-12"
        ],
        [
          14,
          "15"
        ],
        [
          15,
          "19"
        ],
        [
          16,
          "-10"
        ],
        [
          17,
          "-8"
        ],
        [
          18,
          "-2"
        ],
        [
          19,
          "-2"
        ],
        [
          20,
          "7"
        ],
        [
          21,
          "1"
        ],
        [
          22,
          "-7"
        ],
        [
          23,
          "-6"
        ],
        [
          24,
          "7"
        ],
        [
          25,
          "7"
        ],
        [
          26,
          "-4"
        ],
        [
          27,
          "-5"
        ],
        [
          28,
          "1"
        ],
        [
          29,
          "3"
        ],
        [
          31,
          "-1"
        ]
      ]
    },
    {
      "terms": [
        [
          -6,
          "1"
        ],
        [
          -5,
          "-3"
        ],
        [
          -4,
          "-2"
        ],
        [
          -3,
          "4"
        ],
        [
          -2,
          "2"
        ],
        [
          -1,
          "2"
        ],
        [
          0,
          "-7"
        ],
        [
          1,
          "-2"
        ],
        [
          2,
          "-2"
        ],
        [
          3,
          "2"
        ],
        [
          4,
          "4"
        ],
        [
          5,
          "-5"
        ],
        [
          6,
          "-3"
        ],
        [
          7,
          "2"
        ],
        [
          8,
          "4"
        ],
        [
          9,
          "-1"
        ],
        [
          10,
          "-3"
        ],
        [
          11,
          "-2"
        ],
        [
          12,
          "8"
        ],
        [
          13,
          "6"
        ],
        [
          15,
          "-6"
        ],
        [
          16,
          "-5"
        ],
        [
          17,
          "5"
        ],
        [
          18,
          "4"
        ],
        [
          19,
          "1"
        ],
        [
          20,
          "-2"
        ],
        [
          21,
          "-3"
        ],
        [
          22,
          "1"
        ]
      ]
    },
    {
      "terms": [
        [
          -7,
          "1"
        ],
        [
          -5,
          "-2"
        ],
        [
          -3,
          "1"
        ],
        [
          -2,
          "5"
        ],
        [
          0,
          "-1"
        ],
        [
          1,
          "-4"
        ],
        [
          2,
          "-2"
        ],
        [
          3,
          "4"
        ],
        [
          4,
          "2"
        ],
        [
          5,
          "3"
        ],
        [
          6,
          "-8"
        ],
        [
          7,
          "-5"
        ],
        [
          8,
          "-2"
        ],
        [
          9,
          "5"
        ],
        [
          10,
          "6"
        ],
        [
          11,
          "-2"
        ],
        [
          12,
          "-4"
        ],
        [
          13,
          "-5"
        ],
        [
          14,
          "3"
        ],
        [
          15,
          "6"
        ],
        [
          16,
          "3"
        ],
        [
          17,
          "-2"
        ],
        [
          18,
          "-4"
        ],
        [
          20,
          "2"
        ],
        [
          21,
          "1"
        ],
        [
          23,
          "-1"
        ]
      ]
    },
    {
      "terms": [
        [
          -6,
          "-1"
        ],
        [
          -3,
          "1"
        ],
        [
          -2,
          "-1"
        ],
        [
          -1,
          "-1"
        ],
        [
          2,
          "1"
        ],
        [
          5,
          "-2"
        ],
        [
          7,
          "2"
        ],
        [
          10,
          "-1"
        ],
        [
          13,
          "1"
        ],
        [
          14,
          "1"
        ],
        [
          15,
          "-1"
        ],
        [
          18,
          "1"
        ]
      ]
    }
  ],
  "pn_count": 25,
  "f_pauli_f64": 0.39898918811955825,
  "tr_alt_f64": -1.648263071395541e-7,
  "net_f64": 4.1310970835170457e-7,
  "tr_markov_f64": 9.310068397100868e-9,
  "strands": [],
  "total_words": 10,
  "max_coeff_log10": 10.698970004336019,
  "elapsed_seconds": 0.011581745,
  "computed_at": ""
}